<?xml version="1.0" encoding="utf-8"?>
<LanguageData>

  <GoJuice.label>고주스</GoJuice.label>
  <GoJuice.description>초기 행성간 전쟁 시대에 우주 해군이 발명한 합성 전투약물입니다. 고통을 막고 의식을 향상시켜 사용자의 집중력, 근접전 및 원거리 조준능력을 끌어 올립니다. 또한 대근운동을 촉진해 더 빠르게 움직일 수 있도록 합니다.\n\n발명한 과학자들도 중독성은 제거할 수 없었고, 일부는 이를 단점으로 보았습니다. 그러나 다른 사람들은 장점이라고 여겼습니다.</GoJuice.description>
  <GoJuice.ingestible.ingestCommandString>{0} 투여</GoJuice.ingestible.ingestCommandString>
  <GoJuice.ingestible.ingestReportString>{0} 투여하는 중.</GoJuice.ingestible.ingestReportString>


</LanguageData>