<Defs>

  <ThoughtDef>
    <defName>ScavengingRuins</defName>
    <workerClass>RealRuins.ThoughtWorker_ScavengingRuins</workerClass>
    <validWhileDespawned>true</validWhileDespawned>
    <stages>
      <li>
        <label>low wealth ruins</label>
        <description>Did we really have to go that far just for stones and trash?</description>
        <baseMoodEffect>-3</baseMoodEffect>
      </li>
      <li>
        <label>medium wealth ruins</label>
        <description>Looks like we can find some really useful things here</description>
        <baseMoodEffect>+5</baseMoodEffect>
      </li>
      <li>
        <label>high wealth ruins</label>
        <description>This journey was definitely worth it.</description>
        <baseMoodEffect>+15</baseMoodEffect>
      </li>
      <li>
        <label>very high wealth ruins</label>
        <description>There is a whole fortune here! We should take everything and I will fight for it!</description>
        <baseMoodEffect>+25</baseMoodEffect>
      </li>
      <li>
        <label>insanely wealth ruins</label>
        <description>OH MY THAT'S INSANE SUCH WEALTH MUCH MONEY</description>
        <baseMoodEffect>+40</baseMoodEffect>
      </li>
    </stages>
  </ThoughtDef>

</Defs>