<?xml version="1.0" encoding="utf-8"?>
<LanguageData>

	<!--
	<MakeAmmo_30Carbine_FMJ.label>Изготовить пачку патронов .30 Carbine (FMJ) (500 шт.)</MakeAmmo_30Carbine_FMJ.label>
	<MakeAmmo_30Carbine_FMJ.description>Изготовить 500 патронов .30 Carbine (FMJ).</MakeAmmo_30Carbine_FMJ.description>
	<MakeAmmo_30Carbine_FMJ.jobString>делать патрон .30 Carbine (FMJ)</MakeAmmo_30Carbine_FMJ.jobString>

	<MakeAmmo_30Carbine_AP.label>Изготовить пачку патронов .30 Carbine (AP) (500 шт.)</MakeAmmo_30Carbine_AP.label>
	<MakeAmmo_30Carbine_AP.description>Изготовить 500 патронов .30 Carbine (AP).</MakeAmmo_30Carbine_AP.description>
	<MakeAmmo_30Carbine_AP.jobString>Изготавливает патроны .30 Carbine (AP)</MakeAmmo_30Carbine_AP.jobString>

	<MakeAmmo_30Carbine_HP.label>Изготовить пачку патронов .30 Carbine (HP) (500 шт.)</MakeAmmo_30Carbine_HP.label>
	<MakeAmmo_30Carbine_HP.description>Изготовить 500 патронов .30 Carbine (HP).</MakeAmmo_30Carbine_HP.description>
	<MakeAmmo_30Carbine_HP.jobString>делать патрон .30 Carbine (HP)</MakeAmmo_30Carbine_HP.jobString>

	<MakeAmmo_30Carbine_Incendiary.label>Изготовить пачку патронов .30 Carbine (AP-I) (500 шт.)</MakeAmmo_30Carbine_Incendiary.label>
	<MakeAmmo_30Carbine_Incendiary.description>Изготовить 500 патронов .30 Carbine (AP-I).</MakeAmmo_30Carbine_Incendiary.description>
	<MakeAmmo_30Carbine_Incendiary.jobString>Изготавливает патроны .30 Carbine (AP-I)</MakeAmmo_30Carbine_Incendiary.jobString>

	<MakeAmmo_30Carbine_HE.label>Изготовить пачку патронов .30 Carbine (AP-HE) (500 шт.)</MakeAmmo_30Carbine_HE.label>
	<MakeAmmo_30Carbine_HE.description>Изготовить 500 патронов .30 Carbine (AP-HE).</MakeAmmo_30Carbine_HE.description>
	<MakeAmmo_30Carbine_HE.jobString>Изготавливает патроны .30 Carbine (AP-HE)</MakeAmmo_30Carbine_HE.jobString>

	<MakeAmmo_30Carbine_Sabot.label>Изготовить пачку патронов .30 Carbine (Sabot) (500 шт.)</MakeAmmo_30Carbine_Sabot.label>
	<MakeAmmo_30Carbine_Sabot.description>Изготовить 500 патронов .30 Carbine (Sabot).</MakeAmmo_30Carbine_Sabot.description>
	<MakeAmmo_30Carbine_Sabot.jobString>Изготавливает патроны .30 Carbine (Sabot)</MakeAmmo_30Carbine_Sabot.jobString>
	-->

</LanguageData>