<?xml version="1.0" encoding="utf-8"?>
<NodeCanvas type="GeologicalLandforms.GraphEditor.Landform">
	<EditorStates>
		<EditorState selected="" pan="0,0" zoom="1" />
	</EditorStates>
	<Groups />
	<Nodes>
		<Node name="Custom Landform" ID="0" type="landformManifest" pos="-950,-517">
			<string name="Id">CaveEntrance</string>
			<boolean name="IsCustom">false</boolean>
			<boolean name="IsExperimental">false</boolean>
			<int name="RevisionVersion">1</int>
			<long name="TimeCreated">1678046041868</long>
			<boolean name="IsEdited">false</boolean>
			<string name="DisplayName" />
			<boolean name="DisplayNameHasDirection">true</boolean>
			<int name="RandSeed">1333644392</int>
		</Node>
		<Node name="World Tile Requirements" ID="1" type="worldTileReq" pos="-950,-517">
			<Topology name="Topology">CaveEntrance</Topology>
			<float name="Commonness">1</float>
			<float name="CaveChance">1</float>
			<FloatRange xmlns:xsd="http://www.w3.org/2001/XMLSchema" xmlns:xsi="http://www.w3.org/2001/XMLSchema-instance" name="HillinessRequirement">
				<min>6</min>
				<max>6</max>
			</FloatRange>
			<FloatRange xmlns:xsd="http://www.w3.org/2001/XMLSchema" xmlns:xsi="http://www.w3.org/2001/XMLSchema-instance" name="RoadRequirement">
				<min>0</min>
				<max>1</max>
			</FloatRange>
			<FloatRange xmlns:xsd="http://www.w3.org/2001/XMLSchema" xmlns:xsi="http://www.w3.org/2001/XMLSchema-instance" name="RiverRequirement">
				<min>0</min>
				<max>1</max>
			</FloatRange>
			<FloatRange xmlns:xsd="http://www.w3.org/2001/XMLSchema" xmlns:xsi="http://www.w3.org/2001/XMLSchema-instance" name="ElevationRequirement">
				<min>-1000</min>
				<max>5000</max>
			</FloatRange>
			<FloatRange xmlns:xsd="http://www.w3.org/2001/XMLSchema" xmlns:xsi="http://www.w3.org/2001/XMLSchema-instance" name="AvgTemperatureRequirement">
				<min>-100</min>
				<max>100</max>
			</FloatRange>
			<FloatRange xmlns:xsd="http://www.w3.org/2001/XMLSchema" xmlns:xsi="http://www.w3.org/2001/XMLSchema-instance" name="RainfallRequirement">
				<min>0</min>
				<max>5000</max>
			</FloatRange>
			<FloatRange xmlns:xsd="http://www.w3.org/2001/XMLSchema" xmlns:xsi="http://www.w3.org/2001/XMLSchema-instance" name="SwampinessRequirement">
				<min>0</min>
				<max>1</max>
			</FloatRange>
			<FloatRange xmlns:xsd="http://www.w3.org/2001/XMLSchema" xmlns:xsi="http://www.w3.org/2001/XMLSchema-instance" name="MapSizeRequirement">
				<min>50</min>
				<max>1000</max>
			</FloatRange>
			<FloatRange xmlns:xsd="http://www.w3.org/2001/XMLSchema" xmlns:xsi="http://www.w3.org/2001/XMLSchema-instance" name="BiomeTransitionsRequirement">
				<min>0</min>
				<max>6</max>
			</FloatRange>
			<FloatRange xmlns:xsd="http://www.w3.org/2001/XMLSchema" xmlns:xsi="http://www.w3.org/2001/XMLSchema-instance" name="TopologyValueRequirement">
				<min>-1</min>
				<max>1</max>
			</FloatRange>
			<FloatRange xmlns:xsd="http://www.w3.org/2001/XMLSchema" xmlns:xsi="http://www.w3.org/2001/XMLSchema-instance" name="DepthInCaveSystemRequirement">
				<min>0</min>
				<max>10</max>
			</FloatRange>
			<boolean name="AllowSettlements">false</boolean>
			<boolean name="AllowSites">false</boolean>
			<int name="RandSeed">351232153</int>
		</Node>
		<Node name="Perlin Noise" ID="2" type="gridPerlin" pos="-192.0002,-467.8">
			<Port ID="0" name="FrequencyKnob" dynamic="False" />
			<Port ID="1" name="LacunarityKnob" dynamic="False" />
			<Port ID="2" name="PersistenceKnob" dynamic="False" />
			<Port ID="3" name="ScaleKnob" dynamic="False" />
			<Port ID="4" name="BiasKnob" dynamic="False" />
			<Port ID="5" name="OutputKnob" dynamic="False" />
			<double name="Frequency">0.020999999716877937</double>
			<double name="Lacunarity">2</double>
			<double name="Persistence">0.5</double>
			<double name="Scale">0.40000000596046448</double>
			<double name="Bias">0.40000000596046448</double>
			<int name="Octaves">6</int>
			<boolean name="DynamicSeed">false</boolean>
			<int name="RandSeed">1409214904</int>
		</Node>
		<Node name="Elevation Output" ID="3" type="outputElevation" pos="1155.6,-224.8">
			<Port ID="6" name="InputKnob" dynamic="False" />
			<Port ID="7" name="OutputKnob" dynamic="False" />
			<int name="RandSeed">1888083133</int>
		</Node>
		<Node name="Add" ID="4" type="gridOperator" pos="587,-300.8">
			<Port ID="8" name="OutputKnob" dynamic="False" />
			<Port ID="9" name="Input 0" dynamic="True" type="NodeEditorFramework.ValueConnectionKnob, TerrainGraph, Version=1.1.3.0, Culture=neutral, PublicKeyToken=null">
				<string name="styleID">GridFunc</string>
				<Direction name="direction">In</Direction>
				<ConnectionCount name="maxConnectionCount">Single</ConnectionCount>
				<NodeSide name="side">Left</NodeSide>
				<float name="sidePosition">38</float>
				<float name="sideOffset">0</float>
			</Port>
			<Port ID="10" name="Input 1" dynamic="True" type="NodeEditorFramework.ValueConnectionKnob, TerrainGraph, Version=1.1.3.0, Culture=neutral, PublicKeyToken=null">
				<string name="styleID">GridFunc</string>
				<Direction name="direction">In</Direction>
				<ConnectionCount name="maxConnectionCount">Single</ConnectionCount>
				<NodeSide name="side">Left</NodeSide>
				<float name="sidePosition">66</float>
				<float name="sideOffset">0</float>
			</Port>
			<Variable name="Values" refID="0" />
			<Operation name="OperationType">Add</Operation>
			<double name="ApplyChance">1</double>
			<double name="StackCount">1</double>
			<double name="Smoothness">0</double>
			<int name="RandSeed">2008654988</int>
		</Node>
		<Node name="Map Sides" ID="5" type="gridRotateToMapSides" pos="90.2,-181">
			<Port ID="11" name="Input 0" dynamic="True" type="NodeEditorFramework.ValueConnectionKnob, TerrainGraph, Version=1.1.3.0, Culture=neutral, PublicKeyToken=null">
				<string name="styleID">GridFunc</string>
				<Direction name="direction">In</Direction>
				<ConnectionCount name="maxConnectionCount">Single</ConnectionCount>
				<NodeSide name="side">Left</NodeSide>
				<float name="sidePosition">38</float>
				<float name="sideOffset">0</float>
			</Port>
			<Port ID="12" name="Output 0" dynamic="True" type="NodeEditorFramework.ValueConnectionKnob, TerrainGraph, Version=1.1.3.0, Culture=neutral, PublicKeyToken=null">
				<string name="styleID">GridFunc</string>
				<Direction name="direction">Out</Direction>
				<ConnectionCount name="maxConnectionCount">Multi</ConnectionCount>
				<NodeSide name="side">Right</NodeSide>
				<float name="sidePosition">38</float>
				<float name="sideOffset">0</float>
			</Port>
			<Variable name="MapSides" refID="1" />
			<int name="RandSeed">1749960434</int>
		</Node>
		<Node name="Linear Function" ID="6" type="gridLinear" pos="-193,-239">
			<Port ID="13" name="OutputKnob" dynamic="False" />
			<Port ID="14" name="Bias" dynamic="True" type="NodeEditorFramework.ValueConnectionKnob, TerrainGraph, Version=1.1.3.0, Culture=neutral, PublicKeyToken=null">
				<string name="styleID">ValueFunc</string>
				<Direction name="direction">In</Direction>
				<ConnectionCount name="maxConnectionCount">Single</ConnectionCount>
				<NodeSide name="side">Left</NodeSide>
				<float name="sidePosition">38</float>
				<float name="sideOffset">0</float>
			</Port>
			<Port ID="15" name="Origin x" dynamic="True" type="NodeEditorFramework.ValueConnectionKnob, TerrainGraph, Version=1.1.3.0, Culture=neutral, PublicKeyToken=null">
				<string name="styleID">ValueFunc</string>
				<Direction name="direction">In</Direction>
				<ConnectionCount name="maxConnectionCount">Single</ConnectionCount>
				<NodeSide name="side">Left</NodeSide>
				<float name="sidePosition">122</float>
				<float name="sideOffset">0</float>
			</Port>
			<Port ID="16" name="Span px" dynamic="True" type="NodeEditorFramework.ValueConnectionKnob, TerrainGraph, Version=1.1.3.0, Culture=neutral, PublicKeyToken=null">
				<string name="styleID">ValueFunc</string>
				<Direction name="direction">In</Direction>
				<ConnectionCount name="maxConnectionCount">Single</ConnectionCount>
				<NodeSide name="side">Left</NodeSide>
				<float name="sidePosition">150</float>
				<float name="sideOffset">0</float>
			</Port>
			<Port ID="17" name="Clamp min" dynamic="True" type="NodeEditorFramework.ValueConnectionKnob, TerrainGraph, Version=1.1.3.0, Culture=neutral, PublicKeyToken=null">
				<string name="styleID">ValueFunc</string>
				<Direction name="direction">In</Direction>
				<ConnectionCount name="maxConnectionCount">Single</ConnectionCount>
				<NodeSide name="side">Left</NodeSide>
				<float name="sidePosition">66</float>
				<float name="sideOffset">0</float>
			</Port>
			<Port ID="18" name="Clamp max" dynamic="True" type="NodeEditorFramework.ValueConnectionKnob, TerrainGraph, Version=1.1.3.0, Culture=neutral, PublicKeyToken=null">
				<string name="styleID">ValueFunc</string>
				<Direction name="direction">In</Direction>
				<ConnectionCount name="maxConnectionCount">Single</ConnectionCount>
				<NodeSide name="side">Left</NodeSide>
				<float name="sidePosition">94</float>
				<float name="sideOffset">0</float>
			</Port>
			<Port ID="19" name="Span nx" dynamic="True" type="NodeEditorFramework.ValueConnectionKnob, TerrainGraph, Version=1.1.3.0, Culture=neutral, PublicKeyToken=null">
				<string name="styleID">ValueFunc</string>
				<Direction name="direction">In</Direction>
				<ConnectionCount name="maxConnectionCount">Single</ConnectionCount>
				<NodeSide name="side">Left</NodeSide>
				<float name="sidePosition">178</float>
				<float name="sideOffset">0</float>
			</Port>
			<double name="Bias">1</double>
			<double name="ClampMin">0</double>
			<double name="ClampMax">1</double>
			<double name="OriginX">0.44999998807907104</double>
			<double name="OriginZ">0</double>
			<double name="SpanPx">-70.689124829529121</double>
			<double name="SpanNx">0</double>
			<double name="SpanPz">0</double>
			<double name="SpanNz">0</double>
			<boolean name="Circular">false</boolean>
			<int name="RandSeed">1352135021</int>
		</Node>
		<Node name="Random Value" ID="7" type="valueRandom" pos="-478,-182">
			<Port ID="20" name="AverageKnob" dynamic="False" />
			<Port ID="21" name="DeviationKnob" dynamic="False" />
			<Port ID="22" name="OutputKnob" dynamic="False" />
			<double name="Average">-60</double>
			<double name="Deviation">15</double>
			<boolean name="DynamicSeed">true</boolean>
			<int name="RandSeed">269705473</int>
		</Node>
		<Node name="Scatterers" ID="8" type="outputScatterers" pos="1900.802,241.4001">
			<Port ID="23" name="MineablesKnob" dynamic="False" />
			<Port ID="24" name="CaveHivesKnob" dynamic="False" />
			<int name="RandSeed">1028810936</int>
		</Node>
		<Node name="Random Value" ID="9" type="valueRandom" pos="1598.801,202.6001">
			<Port ID="25" name="AverageKnob" dynamic="False" />
			<Port ID="26" name="DeviationKnob" dynamic="False" />
			<Port ID="27" name="OutputKnob" dynamic="False" />
			<double name="Average">24</double>
			<double name="Deviation">4</double>
			<boolean name="DynamicSeed">false</boolean>
			<int name="RandSeed">533971157</int>
		</Node>
		<Node name="Caves Output" ID="10" type="outputCaves" pos="3489,188.6">
			<Port ID="28" name="InputKnob" dynamic="False" />
			<Port ID="29" name="OutputKnob" dynamic="False" />
			<int name="RandSeed">1750516046</int>
		</Node>
		<Node name="Preview" ID="11" type="gridPreview" pos="2757.8,24.80011">
			<Port ID="30" name="InputKnob" dynamic="False" />
			<Port ID="31" name="OutputKnob" dynamic="False" />
			<string name="PreviewModelId">Default</string>
			<int name="RandSeed">431008096</int>
		</Node>
		<Node name="Preview" ID="12" type="gridPreview" pos="301.2003,-373.6">
			<Port ID="32" name="InputKnob" dynamic="False" />
			<Port ID="33" name="OutputKnob" dynamic="False" />
			<string name="PreviewModelId">Default</string>
			<int name="RandSeed">1902503282</int>
		</Node>
		<Node name="Preview" ID="13" type="gridPreview" pos="301.2002,-216.2">
			<Port ID="34" name="InputKnob" dynamic="False" />
			<Port ID="35" name="OutputKnob" dynamic="False" />
			<string name="PreviewModelId">Default</string>
			<int name="RandSeed">815184371</int>
		</Node>
		<Node name="Preview" ID="14" type="gridPreview" pos="870.2,-273">
			<Port ID="36" name="InputKnob" dynamic="False" />
			<Port ID="37" name="OutputKnob" dynamic="False" />
			<string name="PreviewModelId">Elevation</string>
			<int name="RandSeed">49627439</int>
		</Node>
		<Node name="Tunnels" ID="15" type="gridTunnels" pos="2428.6,-77.8">
			<Port ID="38" name="InputKnob" dynamic="False" />
			<Port ID="39" name="OutputKnob" dynamic="False" />
			<double name="InputThreshold">0.699999988079071</double>
			<double name="OpenTunnelsPer10K">10</double>
			<double name="ClosedTunnelsPer10K">0</double>
			<int name="MaxOpenTunnelsPerRockGroup">10</int>
			<int name="MaxClosedTunnelsPerRockGroup">0</int>
			<double name="TunnelWidthMultiplierMin">0.800000011920929</double>
			<double name="TunnelWidthMultiplierMax">2.2999999523162842</double>
			<double name="WidthReductionPerCell">0.039999999105930328</double>
			<double name="BranchChance">0.014999999664723873</double>
			<int name="BranchMinDistanceFromStart">25</int>
			<double name="BranchWidthOffsetMultiplier">0.5</double>
			<double name="DirectionChangeSpeed">8</double>
			<int name="RandSeed">230599817</int>
		</Node>
		<Node name="World Tile Graphic" ID="16" type="worldTileGraphic" pos="584.2,-455.8">
			<DrawMode name="DrawMode">HexAdjacencyCaves</DrawMode>
			<int name="AtlasSizeX">4</int>
			<int name="AtlasSizeY">4</int>
			<int name="RandSeed">324907296</int>
		</Node>
		<Node name="Dynamic Random Value" ID="17" type="valueRandom" pos="1600.201,313.9998">
			<Port ID="40" name="AverageKnob" dynamic="False" />
			<Port ID="41" name="DeviationKnob" dynamic="False" />
			<Port ID="42" name="OutputKnob" dynamic="False" />
			<double name="Average">0.5</double>
			<double name="Deviation">0.20000000298023224</double>
			<boolean name="DynamicSeed">false</boolean>
			<int name="RandSeed">568688265</int>
		</Node>
		<Node name="Linear Function" ID="18" type="gridLinear" pos="-195.2,218.7999">
			<Port ID="43" name="OutputKnob" dynamic="False" />
			<Port ID="44" name="Bias" dynamic="True" type="NodeEditorFramework.ValueConnectionKnob, TerrainGraph, Version=1.1.3.0, Culture=neutral, PublicKeyToken=null">
				<string name="styleID">ValueFunc</string>
				<Direction name="direction">In</Direction>
				<ConnectionCount name="maxConnectionCount">Single</ConnectionCount>
				<NodeSide name="side">Left</NodeSide>
				<float name="sidePosition">38</float>
				<float name="sideOffset">0</float>
			</Port>
			<Port ID="45" name="Origin x" dynamic="True" type="NodeEditorFramework.ValueConnectionKnob, TerrainGraph, Version=1.1.3.0, Culture=neutral, PublicKeyToken=null">
				<string name="styleID">ValueFunc</string>
				<Direction name="direction">In</Direction>
				<ConnectionCount name="maxConnectionCount">Single</ConnectionCount>
				<NodeSide name="side">Left</NodeSide>
				<float name="sidePosition">66</float>
				<float name="sideOffset">0</float>
			</Port>
			<Port ID="46" name="Span px" dynamic="True" type="NodeEditorFramework.ValueConnectionKnob, TerrainGraph, Version=1.1.3.0, Culture=neutral, PublicKeyToken=null">
				<string name="styleID">ValueFunc</string>
				<Direction name="direction">In</Direction>
				<ConnectionCount name="maxConnectionCount">Single</ConnectionCount>
				<NodeSide name="side">Left</NodeSide>
				<float name="sidePosition">94</float>
				<float name="sideOffset">0</float>
			</Port>
			<double name="Bias">-2</double>
			<double name="ClampMin">-1.7976931348623157E+308</double>
			<double name="ClampMax">1.7976931348623157E+308</double>
			<double name="OriginX">0.12391903564677043</double>
			<double name="OriginZ">0</double>
			<double name="SpanPx">50</double>
			<double name="SpanNx">50</double>
			<double name="SpanPz">0</double>
			<double name="SpanNz">0</double>
			<boolean name="Circular">false</boolean>
			<int name="RandSeed">250640113</int>
		</Node>
		<Node name="Preview" ID="19" type="gridPreview" pos="877.8001,129.5999">
			<Port ID="47" name="InputKnob" dynamic="False" />
			<Port ID="48" name="OutputKnob" dynamic="False" />
			<string name="PreviewModelId">Default</string>
			<int name="RandSeed">354703711</int>
		</Node>
		<Node name="Perlin Noise" ID="20" type="gridPerlin" pos="-193.8001,-5.799896">
			<Port ID="49" name="FrequencyKnob" dynamic="False" />
			<Port ID="50" name="LacunarityKnob" dynamic="False" />
			<Port ID="51" name="PersistenceKnob" dynamic="False" />
			<Port ID="52" name="ScaleKnob" dynamic="False" />
			<Port ID="53" name="BiasKnob" dynamic="False" />
			<Port ID="54" name="OutputKnob" dynamic="False" />
			<double name="Frequency">0.0040000001899898052</double>
			<double name="Lacunarity">2</double>
			<double name="Persistence">0.5</double>
			<double name="Scale">0.5</double>
			<double name="Bias">0.5</double>
			<int name="Octaves">6</int>
			<boolean name="DynamicSeed">false</boolean>
			<int name="RandSeed">75979624</int>
		</Node>
		<Node name="Add" ID="21" type="gridOperator" pos="297.2001,117.8">
			<Port ID="55" name="OutputKnob" dynamic="False" />
			<Port ID="56" name="Input 0" dynamic="True" type="NodeEditorFramework.ValueConnectionKnob, TerrainGraph, Version=1.1.3.0, Culture=neutral, PublicKeyToken=null">
				<string name="styleID">GridFunc</string>
				<Direction name="direction">In</Direction>
				<ConnectionCount name="maxConnectionCount">Single</ConnectionCount>
				<NodeSide name="side">Left</NodeSide>
				<float name="sidePosition">38</float>
				<float name="sideOffset">0</float>
			</Port>
			<Port ID="57" name="Input 1" dynamic="True" type="NodeEditorFramework.ValueConnectionKnob, TerrainGraph, Version=1.1.3.0, Culture=neutral, PublicKeyToken=null">
				<string name="styleID">GridFunc</string>
				<Direction name="direction">In</Direction>
				<ConnectionCount name="maxConnectionCount">Single</ConnectionCount>
				<NodeSide name="side">Left</NodeSide>
				<float name="sidePosition">66</float>
				<float name="sideOffset">0</float>
			</Port>
			<Variable name="Values" refID="2" />
			<Operation name="OperationType">Add</Operation>
			<double name="ApplyChance">1</double>
			<double name="StackCount">1</double>
			<double name="Smoothness">0</double>
			<int name="RandSeed">1076128167</int>
		</Node>
		<Node name="Add" ID="22" type="gridOperator" pos="1078.6,181.5999">
			<Port ID="58" name="OutputKnob" dynamic="False" />
			<Port ID="59" name="Input 0" dynamic="True" type="NodeEditorFramework.ValueConnectionKnob, TerrainGraph, Version=1.1.3.0, Culture=neutral, PublicKeyToken=null">
				<string name="styleID">GridFunc</string>
				<Direction name="direction">In</Direction>
				<ConnectionCount name="maxConnectionCount">Single</ConnectionCount>
				<NodeSide name="side">Left</NodeSide>
				<float name="sidePosition">38</float>
				<float name="sideOffset">0</float>
			</Port>
			<Port ID="60" name="Input 1" dynamic="True" type="NodeEditorFramework.ValueConnectionKnob, TerrainGraph, Version=1.1.3.0, Culture=neutral, PublicKeyToken=null">
				<string name="styleID">GridFunc</string>
				<Direction name="direction">In</Direction>
				<ConnectionCount name="maxConnectionCount">Single</ConnectionCount>
				<NodeSide name="side">Left</NodeSide>
				<float name="sidePosition">66</float>
				<float name="sideOffset">0</float>
			</Port>
			<Variable name="Values" refID="3" />
			<Operation name="OperationType">Invert_Above</Operation>
			<double name="ApplyChance">1</double>
			<double name="StackCount">1</double>
			<double name="Smoothness">0</double>
			<int name="RandSeed">63859700</int>
		</Node>
		<Node name="Preview" ID="23" type="gridPreview" pos="1380.6,97.59999">
			<Port ID="61" name="InputKnob" dynamic="False" />
			<Port ID="62" name="OutputKnob" dynamic="False" />
			<string name="PreviewModelId">Default</string>
			<int name="RandSeed">1583950093</int>
		</Node>
		<Node name="Preview" ID="24" type="gridPreview" pos="1941.4,-32.40002">
			<Port ID="63" name="InputKnob" dynamic="False" />
			<Port ID="64" name="OutputKnob" dynamic="False" />
			<string name="PreviewModelId">Elevation</string>
			<int name="RandSeed">833598219</int>
		</Node>
		<Node name="Dynamic Random Value" ID="25" type="valueRandom" pos="-476.7999,217.4">
			<Port ID="65" name="AverageKnob" dynamic="False" />
			<Port ID="66" name="DeviationKnob" dynamic="False" />
			<Port ID="67" name="OutputKnob" dynamic="False" />
			<double name="Average">0</double>
			<double name="Deviation">0.20000000298023224</double>
			<boolean name="DynamicSeed">false</boolean>
			<int name="RandSeed">582941670</int>
		</Node>
		<Node name="Map Sides" ID="26" type="gridRotateToMapSides" pos="87.00051,184.2">
			<Port ID="68" name="Input 0" dynamic="True" type="NodeEditorFramework.ValueConnectionKnob, TerrainGraph, Version=1.1.3.0, Culture=neutral, PublicKeyToken=null">
				<string name="styleID">GridFunc</string>
				<Direction name="direction">In</Direction>
				<ConnectionCount name="maxConnectionCount">Single</ConnectionCount>
				<NodeSide name="side">Left</NodeSide>
				<float name="sidePosition">38</float>
				<float name="sideOffset">0</float>
			</Port>
			<Port ID="69" name="Output 0" dynamic="True" type="NodeEditorFramework.ValueConnectionKnob, TerrainGraph, Version=1.1.3.0, Culture=neutral, PublicKeyToken=null">
				<string name="styleID">GridFunc</string>
				<Direction name="direction">Out</Direction>
				<ConnectionCount name="maxConnectionCount">Multi</ConnectionCount>
				<NodeSide name="side">Right</NodeSide>
				<float name="sidePosition">38</float>
				<float name="sideOffset">0</float>
			</Port>
			<Variable name="MapSides" refID="4" />
			<int name="RandSeed">1739817022</int>
		</Node>
		<Node name="Rotate" ID="27" type="gridRotate" pos="588.4006,167.5999">
			<Port ID="70" name="InputKnob" dynamic="False" />
			<Port ID="71" name="AngleKnob" dynamic="False" />
			<Port ID="72" name="OutputKnob" dynamic="False" />
			<double name="Angle">-19.095105245731563</double>
			<int name="RandSeed">422074182</int>
		</Node>
		<Node name="Dynamic Random Value" ID="28" type="valueRandom" pos="298.6004,235.2">
			<Port ID="73" name="AverageKnob" dynamic="False" />
			<Port ID="74" name="DeviationKnob" dynamic="False" />
			<Port ID="75" name="OutputKnob" dynamic="False" />
			<double name="Average">0</double>
			<double name="Deviation">25</double>
			<boolean name="DynamicSeed">false</boolean>
			<int name="RandSeed">773369775</int>
		</Node>
		<Node name="Select" ID="29" type="gridSelectValue" pos="1597.4,11.39995">
			<Port ID="76" name="InputKnob" dynamic="False" />
			<Port ID="77" name="OutputKnob" dynamic="False" />
			<Port ID="78" name="Option 0" dynamic="True" type="NodeEditorFramework.ValueConnectionKnob, TerrainGraph, Version=1.1.3.0, Culture=neutral, PublicKeyToken=null">
				<string name="styleID">GridFunc</string>
				<Direction name="direction">In</Direction>
				<ConnectionCount name="maxConnectionCount">Single</ConnectionCount>
				<NodeSide name="side">Left</NodeSide>
				<float name="sidePosition">66</float>
				<float name="sideOffset">0</float>
			</Port>
			<Port ID="79" name="Option 1" dynamic="True" type="NodeEditorFramework.ValueConnectionKnob, TerrainGraph, Version=1.1.3.0, Culture=neutral, PublicKeyToken=null">
				<string name="styleID">GridFunc</string>
				<Direction name="direction">In</Direction>
				<ConnectionCount name="maxConnectionCount">Single</ConnectionCount>
				<NodeSide name="side">Left</NodeSide>
				<float name="sidePosition">94</float>
				<float name="sideOffset">0</float>
			</Port>
			<Variable name="Values" refID="5" />
			<Variable name="Thresholds" refID="6" />
			<int name="RandSeed">268207354</int>
		</Node>
		<Node name="Add" ID="30" type="gridOperator" pos="1597,-98.20001">
			<Port ID="80" name="OutputKnob" dynamic="False" />
			<Port ID="81" name="Input 0" dynamic="True" type="NodeEditorFramework.ValueConnectionKnob, TerrainGraph, Version=1.1.3.0, Culture=neutral, PublicKeyToken=null">
				<string name="styleID">GridFunc</string>
				<Direction name="direction">In</Direction>
				<ConnectionCount name="maxConnectionCount">Single</ConnectionCount>
				<NodeSide name="side">Left</NodeSide>
				<float name="sidePosition">38</float>
				<float name="sideOffset">0</float>
			</Port>
			<Port ID="82" name="Input 1" dynamic="True" type="NodeEditorFramework.ValueConnectionKnob, TerrainGraph, Version=1.1.3.0, Culture=neutral, PublicKeyToken=null">
				<string name="styleID">GridFunc</string>
				<Direction name="direction">In</Direction>
				<ConnectionCount name="maxConnectionCount">Single</ConnectionCount>
				<NodeSide name="side">Left</NodeSide>
				<float name="sidePosition">66</float>
				<float name="sideOffset">0</float>
			</Port>
			<Variable name="Values" refID="7" />
			<Operation name="OperationType">Invert</Operation>
			<double name="ApplyChance">1</double>
			<double name="StackCount">1</double>
			<double name="Smoothness">0</double>
			<int name="RandSeed">1421633023</int>
		</Node>
		<Node name="Preview" ID="31" type="gridPreview" pos="2758.6,185.2">
			<Port ID="83" name="InputKnob" dynamic="False" />
			<Port ID="84" name="OutputKnob" dynamic="False" />
			<string name="PreviewModelId">Default</string>
			<int name="RandSeed">1302405403</int>
		</Node>
		<Node name="Select" ID="32" type="gridSelectValue" pos="2160.2,74.79996">
			<Port ID="85" name="InputKnob" dynamic="False" />
			<Port ID="86" name="OutputKnob" dynamic="False" />
			<Port ID="87" name="Option 0" dynamic="True" type="NodeEditorFramework.ValueConnectionKnob, TerrainGraph, Version=1.1.3.0, Culture=neutral, PublicKeyToken=null">
				<string name="styleID">GridFunc</string>
				<Direction name="direction">In</Direction>
				<ConnectionCount name="maxConnectionCount">Single</ConnectionCount>
				<NodeSide name="side">Left</NodeSide>
				<float name="sidePosition">66</float>
				<float name="sideOffset">0</float>
			</Port>
			<Port ID="88" name="Option 1" dynamic="True" type="NodeEditorFramework.ValueConnectionKnob, TerrainGraph, Version=1.1.3.0, Culture=neutral, PublicKeyToken=null">
				<string name="styleID">GridFunc</string>
				<Direction name="direction">In</Direction>
				<ConnectionCount name="maxConnectionCount">Single</ConnectionCount>
				<NodeSide name="side">Left</NodeSide>
				<float name="sidePosition">94</float>
				<float name="sideOffset">0</float>
			</Port>
			<Variable name="Values" refID="8" />
			<Variable name="Thresholds" refID="9" />
			<int name="RandSeed">1047266028</int>
		</Node>
		<Node name="Add" ID="33" type="gridOperator" pos="2957,70.59999">
			<Port ID="89" name="OutputKnob" dynamic="False" />
			<Port ID="90" name="Input 0" dynamic="True" type="NodeEditorFramework.ValueConnectionKnob, TerrainGraph, Version=1.1.3.0, Culture=neutral, PublicKeyToken=null">
				<string name="styleID">GridFunc</string>
				<Direction name="direction">In</Direction>
				<ConnectionCount name="maxConnectionCount">Single</ConnectionCount>
				<NodeSide name="side">Left</NodeSide>
				<float name="sidePosition">38</float>
				<float name="sideOffset">0</float>
			</Port>
			<Port ID="91" name="Input 1" dynamic="True" type="NodeEditorFramework.ValueConnectionKnob, TerrainGraph, Version=1.1.3.0, Culture=neutral, PublicKeyToken=null">
				<string name="styleID">GridFunc</string>
				<Direction name="direction">In</Direction>
				<ConnectionCount name="maxConnectionCount">Single</ConnectionCount>
				<NodeSide name="side">Left</NodeSide>
				<float name="sidePosition">66</float>
				<float name="sideOffset">0</float>
			</Port>
			<Variable name="Values" refID="10" />
			<Operation name="OperationType">Max</Operation>
			<double name="ApplyChance">1</double>
			<double name="StackCount">1</double>
			<double name="Smoothness">0</double>
			<int name="RandSeed">1411438753</int>
		</Node>
		<Node name="Preview" ID="34" type="gridPreview" pos="3270,119.6">
			<Port ID="92" name="InputKnob" dynamic="False" />
			<Port ID="93" name="OutputKnob" dynamic="False" />
			<string name="PreviewModelId">Default</string>
			<int name="RandSeed">726299070</int>
		</Node>
		<Node name="Add" ID="35" type="gridOperator" pos="1898.4,-177.6">
			<Port ID="94" name="OutputKnob" dynamic="False" />
			<Port ID="95" name="Input 0" dynamic="True" type="NodeEditorFramework.ValueConnectionKnob, TerrainGraph, Version=1.1.3.0, Culture=neutral, PublicKeyToken=null">
				<string name="styleID">GridFunc</string>
				<Direction name="direction">In</Direction>
				<ConnectionCount name="maxConnectionCount">Single</ConnectionCount>
				<NodeSide name="side">Left</NodeSide>
				<float name="sidePosition">38</float>
				<float name="sideOffset">0</float>
			</Port>
			<Port ID="96" name="Input 1" dynamic="True" type="NodeEditorFramework.ValueConnectionKnob, TerrainGraph, Version=1.1.3.0, Culture=neutral, PublicKeyToken=null">
				<string name="styleID">GridFunc</string>
				<Direction name="direction">In</Direction>
				<ConnectionCount name="maxConnectionCount">Single</ConnectionCount>
				<NodeSide name="side">Left</NodeSide>
				<float name="sidePosition">66</float>
				<float name="sideOffset">0</float>
			</Port>
			<Variable name="Values" refID="11" />
			<Operation name="OperationType">Min</Operation>
			<double name="ApplyChance">1</double>
			<double name="StackCount">1</double>
			<double name="Smoothness">0</double>
			<int name="RandSeed">995437916</int>
		</Node>
		<Node name="Preview" ID="36" type="gridPreview" pos="2205.4,-110.6">
			<Port ID="97" name="InputKnob" dynamic="False" />
			<Port ID="98" name="OutputKnob" dynamic="False" />
			<string name="PreviewModelId">Elevation</string>
			<int name="RandSeed">915043615</int>
		</Node>
		<Node name="Perlin Noise" ID="37" type="gridPerlin" pos="1885,480.8">
			<Port ID="99" name="FrequencyKnob" dynamic="False" />
			<Port ID="100" name="LacunarityKnob" dynamic="False" />
			<Port ID="101" name="PersistenceKnob" dynamic="False" />
			<Port ID="102" name="ScaleKnob" dynamic="False" />
			<Port ID="103" name="BiasKnob" dynamic="False" />
			<Port ID="104" name="OutputKnob" dynamic="False" />
			<double name="Frequency">0.05000000074505806</double>
			<double name="Lacunarity">2</double>
			<double name="Persistence">0.5</double>
			<double name="Scale">1</double>
			<double name="Bias">0</double>
			<int name="Octaves">6</int>
			<boolean name="DynamicSeed">false</boolean>
			<int name="RandSeed">1316790352</int>
		</Node>
		<Node name="Perlin Noise" ID="38" type="gridPerlin" pos="1885,707.6">
			<Port ID="105" name="FrequencyKnob" dynamic="False" />
			<Port ID="106" name="LacunarityKnob" dynamic="False" />
			<Port ID="107" name="PersistenceKnob" dynamic="False" />
			<Port ID="108" name="ScaleKnob" dynamic="False" />
			<Port ID="109" name="BiasKnob" dynamic="False" />
			<Port ID="110" name="OutputKnob" dynamic="False" />
			<double name="Frequency">0.05000000074505806</double>
			<double name="Lacunarity">2</double>
			<double name="Persistence">0.5</double>
			<double name="Scale">1</double>
			<double name="Bias">0</double>
			<int name="Octaves">6</int>
			<boolean name="DynamicSeed">false</boolean>
			<int name="RandSeed">907042742</int>
		</Node>
		<Node name="Perlin Noise" ID="39" type="gridPerlin" pos="1885,935.6">
			<Port ID="111" name="FrequencyKnob" dynamic="False" />
			<Port ID="112" name="LacunarityKnob" dynamic="False" />
			<Port ID="113" name="PersistenceKnob" dynamic="False" />
			<Port ID="114" name="ScaleKnob" dynamic="False" />
			<Port ID="115" name="BiasKnob" dynamic="False" />
			<Port ID="116" name="OutputKnob" dynamic="False" />
			<double name="Frequency">0.10000000149011612</double>
			<double name="Lacunarity">2</double>
			<double name="Persistence">0.5</double>
			<double name="Scale">1</double>
			<double name="Bias">0</double>
			<int name="Octaves">6</int>
			<boolean name="DynamicSeed">false</boolean>
			<int name="RandSeed">1473638930</int>
		</Node>
		<Node name="Select" ID="40" type="gridSelectValue" pos="2211.8,849">
			<Port ID="117" name="InputKnob" dynamic="False" />
			<Port ID="118" name="OutputKnob" dynamic="False" />
			<Port ID="119" name="Option 0" dynamic="True" type="NodeEditorFramework.ValueConnectionKnob, TerrainGraph, Version=1.1.3.0, Culture=neutral, PublicKeyToken=null">
				<string name="styleID">GridFunc</string>
				<Direction name="direction">In</Direction>
				<ConnectionCount name="maxConnectionCount">Single</ConnectionCount>
				<NodeSide name="side">Left</NodeSide>
				<float name="sidePosition">66</float>
				<float name="sideOffset">0</float>
			</Port>
			<Port ID="120" name="Option 1" dynamic="True" type="NodeEditorFramework.ValueConnectionKnob, TerrainGraph, Version=1.1.3.0, Culture=neutral, PublicKeyToken=null">
				<string name="styleID">GridFunc</string>
				<Direction name="direction">In</Direction>
				<ConnectionCount name="maxConnectionCount">Single</ConnectionCount>
				<NodeSide name="side">Left</NodeSide>
				<float name="sidePosition">94</float>
				<float name="sideOffset">0</float>
			</Port>
			<Variable name="Values" refID="12" />
			<Variable name="Thresholds" refID="13" />
			<int name="RandSeed">1467444079</int>
		</Node>
		<Node name="Select" ID="41" type="gridSelectValue" pos="2502.8,751">
			<Port ID="121" name="InputKnob" dynamic="False" />
			<Port ID="122" name="OutputKnob" dynamic="False" />
			<Port ID="123" name="Option 0" dynamic="True" type="NodeEditorFramework.ValueConnectionKnob, TerrainGraph, Version=1.1.3.0, Culture=neutral, PublicKeyToken=null">
				<string name="styleID">GridFunc</string>
				<Direction name="direction">In</Direction>
				<ConnectionCount name="maxConnectionCount">Single</ConnectionCount>
				<NodeSide name="side">Left</NodeSide>
				<float name="sidePosition">66</float>
				<float name="sideOffset">0</float>
			</Port>
			<Port ID="124" name="Option 1" dynamic="True" type="NodeEditorFramework.ValueConnectionKnob, TerrainGraph, Version=1.1.3.0, Culture=neutral, PublicKeyToken=null">
				<string name="styleID">GridFunc</string>
				<Direction name="direction">In</Direction>
				<ConnectionCount name="maxConnectionCount">Single</ConnectionCount>
				<NodeSide name="side">Left</NodeSide>
				<float name="sidePosition">94</float>
				<float name="sideOffset">0</float>
			</Port>
			<Variable name="Values" refID="14" />
			<Variable name="Thresholds" refID="15" />
			<int name="RandSeed">1785690188</int>
		</Node>
		<Node name="Select" ID="42" type="gridSelectValue" pos="2790.8,656">
			<Port ID="125" name="InputKnob" dynamic="False" />
			<Port ID="126" name="OutputKnob" dynamic="False" />
			<Port ID="127" name="Option 0" dynamic="True" type="NodeEditorFramework.ValueConnectionKnob, TerrainGraph, Version=1.1.3.0, Culture=neutral, PublicKeyToken=null">
				<string name="styleID">GridFunc</string>
				<Direction name="direction">In</Direction>
				<ConnectionCount name="maxConnectionCount">Single</ConnectionCount>
				<NodeSide name="side">Left</NodeSide>
				<float name="sidePosition">66</float>
				<float name="sideOffset">0</float>
			</Port>
			<Port ID="128" name="Option 1" dynamic="True" type="NodeEditorFramework.ValueConnectionKnob, TerrainGraph, Version=1.1.3.0, Culture=neutral, PublicKeyToken=null">
				<string name="styleID">GridFunc</string>
				<Direction name="direction">In</Direction>
				<ConnectionCount name="maxConnectionCount">Single</ConnectionCount>
				<NodeSide name="side">Left</NodeSide>
				<float name="sidePosition">94</float>
				<float name="sideOffset">0</float>
			</Port>
			<Variable name="Values" refID="16" />
			<Variable name="Thresholds" refID="17" />
			<int name="RandSeed">1069972885</int>
		</Node>
		<Node name="Select" ID="43" type="gridSelectTerrain" pos="3144.4,746.6">
			<Port ID="129" name="InputKnob" dynamic="False" />
			<Port ID="130" name="OutputKnob" dynamic="False" />
			<Port ID="131" name="Option 0" dynamic="True" type="NodeEditorFramework.ValueConnectionKnob, TerrainGraph, Version=1.1.3.0, Culture=neutral, PublicKeyToken=null">
				<string name="styleID">TerrainFunc</string>
				<Direction name="direction">In</Direction>
				<ConnectionCount name="maxConnectionCount">Single</ConnectionCount>
				<NodeSide name="side">Left</NodeSide>
				<float name="sidePosition">66</float>
				<float name="sideOffset">0</float>
			</Port>
			<Port ID="132" name="Option 1" dynamic="True" type="NodeEditorFramework.ValueConnectionKnob, TerrainGraph, Version=1.1.3.0, Culture=neutral, PublicKeyToken=null">
				<string name="styleID">TerrainFunc</string>
				<Direction name="direction">In</Direction>
				<ConnectionCount name="maxConnectionCount">Single</ConnectionCount>
				<NodeSide name="side">Left</NodeSide>
				<float name="sidePosition">94</float>
				<float name="sideOffset">0</float>
			</Port>
			<Port ID="133" name="Option 2" dynamic="True" type="NodeEditorFramework.ValueConnectionKnob, TerrainGraph, Version=1.1.3.0, Culture=neutral, PublicKeyToken=null">
				<string name="styleID">TerrainFunc</string>
				<Direction name="direction">In</Direction>
				<ConnectionCount name="maxConnectionCount">Single</ConnectionCount>
				<NodeSide name="side">Left</NodeSide>
				<float name="sidePosition">122</float>
				<float name="sideOffset">0</float>
			</Port>
			<Port ID="134" name="Option 3" dynamic="True" type="NodeEditorFramework.ValueConnectionKnob, TerrainGraph, Version=1.1.3.0, Culture=neutral, PublicKeyToken=null">
				<string name="styleID">TerrainFunc</string>
				<Direction name="direction">In</Direction>
				<ConnectionCount name="maxConnectionCount">Single</ConnectionCount>
				<NodeSide name="side">Left</NodeSide>
				<float name="sidePosition">150</float>
				<float name="sideOffset">0</float>
			</Port>
			<Variable name="Values" refID="18" />
			<Variable name="Thresholds" refID="19" />
			<int name="RandSeed">588585345</int>
		</Node>
		<Node name="Preview" ID="44" type="terrainGridPreview" pos="3449.2,649.4">
			<Port ID="135" name="InputKnob" dynamic="False" />
			<Port ID="136" name="OutputKnob" dynamic="False" />
			<Port ID="137" name="ElevationInputKnob" dynamic="False" />
			<Port ID="138" name="ElevationOutputKnob" dynamic="False" />
			<int name="RandSeed">830059435</int>
		</Node>
		<Node name="Terrain Output" ID="45" type="outputTerrain" pos="3674,511.6">
			<Port ID="139" name="BaseKnob" dynamic="False" />
			<Port ID="140" name="StoneKnob" dynamic="False" />
			<Port ID="141" name="CaveKnob" dynamic="False" />
			<int name="RandSeed">276299414</int>
		</Node>
		<Node name="World Tile" ID="46" type="valueWorldTile" pos="2555,996.6">
			<Port ID="142" name="BiomeOutputKnob" dynamic="False" />
			<Port ID="143" name="HillinessOutputKnob" dynamic="False" />
			<Port ID="144" name="ElevationOutputKnob" dynamic="False" />
			<Port ID="145" name="TemperatureOutputKnob" dynamic="False" />
			<Port ID="146" name="RainfallOutputKnob" dynamic="False" />
			<Port ID="147" name="TopologyValueOutputKnob" dynamic="False" />
			<Port ID="148" name="CaveSystemDepthValueOutputKnob" dynamic="False" />
			<int name="RandSeed">308715478</int>
		</Node>
		<Node name="Biome Terrain" ID="47" type="terrainFromBiome" pos="2793,919.6">
			<Port ID="149" name="BiomeKnob" dynamic="False" />
			<Port ID="150" name="FertilityKnob" dynamic="False" />
			<Port ID="151" name="OutputKnob" dynamic="False" />
			<string name="Biome">TemperateForest</string>
			<double name="Fertility">0</double>
			<int name="RandSeed">1254668707</int>
		</Node>
	</Nodes>
	<Connections>
		<Connection port1ID="5" port2ID="32" />
		<Connection port1ID="6" port2ID="37" />
		<Connection port1ID="7" port2ID="76" />
		<Connection port1ID="7" port2ID="95" />
		<Connection port1ID="8" port2ID="36" />
		<Connection port1ID="9" port2ID="33" />
		<Connection port1ID="10" port2ID="35" />
		<Connection port1ID="11" port2ID="13" />
		<Connection port1ID="12" port2ID="34" />
		<Connection port1ID="16" port2ID="22" />
		<Connection port1ID="23" port2ID="27" />
		<Connection port1ID="24" port2ID="42" />
		<Connection port1ID="28" port2ID="93" />
		<Connection port1ID="30" port2ID="39" />
		<Connection port1ID="31" port2ID="90" />
		<Connection port1ID="38" port2ID="98" />
		<Connection port1ID="43" port2ID="68" />
		<Connection port1ID="45" port2ID="67" />
		<Connection port1ID="47" port2ID="72" />
		<Connection port1ID="48" port2ID="59" />
		<Connection port1ID="54" port2ID="56" />
		<Connection port1ID="55" port2ID="70" />
		<Connection port1ID="57" port2ID="69" />
		<Connection port1ID="58" port2ID="61" />
		<Connection port1ID="62" port2ID="79" />
		<Connection port1ID="62" port2ID="81" />
		<Connection port1ID="63" port2ID="77" />
		<Connection port1ID="64" port2ID="85" />
		<Connection port1ID="71" port2ID="75" />
		<Connection port1ID="80" port2ID="96" />
		<Connection port1ID="83" port2ID="86" />
		<Connection port1ID="84" port2ID="91" />
		<Connection port1ID="89" port2ID="92" />
		<Connection port1ID="94" port2ID="97" />
		<Connection port1ID="104" port2ID="125" />
		<Connection port1ID="110" port2ID="121" />
		<Connection port1ID="116" port2ID="117" />
		<Connection port1ID="118" port2ID="123" />
		<Connection port1ID="122" port2ID="127" />
		<Connection port1ID="126" port2ID="129" />
		<Connection port1ID="130" port2ID="135" />
		<Connection port1ID="133" port2ID="151" />
		<Connection port1ID="136" port2ID="141" />
		<Connection port1ID="142" port2ID="149" />
	</Connections>
	<Objects>
		<Object refID="0" type="System.Collections.Generic.List`1[[System.Double, mscorlib, Version=4.0.0.0, Culture=neutral, PublicKeyToken=b77a5c561934e089]]">
			<ArrayOfDouble xmlns:xsd="http://www.w3.org/2001/XMLSchema" xmlns:xsi="http://www.w3.org/2001/XMLSchema-instance">
				<double>0</double>
				<double>0</double>
			</ArrayOfDouble>
		</Object>
		<Object refID="1" type="System.Collections.Generic.List`1[[TerrainGraph.NodeGridRotateToMapSides+MapSide, GeologicalLandforms, Version=1.6.0.0, Culture=neutral, PublicKeyToken=null]]">
			<ArrayOfMapSide xmlns:xsd="http://www.w3.org/2001/XMLSchema" xmlns:xsi="http://www.w3.org/2001/XMLSchema-instance">
				<MapSide>Front</MapSide>
			</ArrayOfMapSide>
		</Object>
		<Object refID="2" type="System.Collections.Generic.List`1[[System.Double, mscorlib, Version=4.0.0.0, Culture=neutral, PublicKeyToken=b77a5c561934e089]]">
			<ArrayOfDouble xmlns:xsd="http://www.w3.org/2001/XMLSchema" xmlns:xsi="http://www.w3.org/2001/XMLSchema-instance">
				<double>0</double>
				<double>0</double>
			</ArrayOfDouble>
		</Object>
		<Object refID="3" type="System.Collections.Generic.List`1[[System.Double, mscorlib, Version=4.0.0.0, Culture=neutral, PublicKeyToken=b77a5c561934e089]]">
			<ArrayOfDouble xmlns:xsd="http://www.w3.org/2001/XMLSchema" xmlns:xsi="http://www.w3.org/2001/XMLSchema-instance">
				<double>0</double>
				<double>0.89999997615814209</double>
			</ArrayOfDouble>
		</Object>
		<Object refID="4" type="System.Collections.Generic.List`1[[TerrainGraph.NodeGridRotateToMapSides+MapSide, GeologicalLandforms, Version=1.6.0.0, Culture=neutral, PublicKeyToken=null]]">
			<ArrayOfMapSide xmlns:xsd="http://www.w3.org/2001/XMLSchema" xmlns:xsi="http://www.w3.org/2001/XMLSchema-instance">
				<MapSide>Left</MapSide>
			</ArrayOfMapSide>
		</Object>
		<Object refID="5" type="System.Collections.Generic.List`1[[System.Double, mscorlib, Version=4.0.0.0, Culture=neutral, PublicKeyToken=b77a5c561934e089]]">
			<ArrayOfDouble xmlns:xsd="http://www.w3.org/2001/XMLSchema" xmlns:xsi="http://www.w3.org/2001/XMLSchema-instance">
				<double>0</double>
				<double>0</double>
			</ArrayOfDouble>
		</Object>
		<Object refID="6" type="System.Collections.Generic.List`1[[System.Double, mscorlib, Version=4.0.0.0, Culture=neutral, PublicKeyToken=b77a5c561934e089]]">
			<ArrayOfDouble xmlns:xsd="http://www.w3.org/2001/XMLSchema" xmlns:xsi="http://www.w3.org/2001/XMLSchema-instance">
				<double>0.699999988079071</double>
			</ArrayOfDouble>
		</Object>
		<Object refID="7" type="System.Collections.Generic.List`1[[System.Double, mscorlib, Version=4.0.0.0, Culture=neutral, PublicKeyToken=b77a5c561934e089]]">
			<ArrayOfDouble xmlns:xsd="http://www.w3.org/2001/XMLSchema" xmlns:xsi="http://www.w3.org/2001/XMLSchema-instance">
				<double>0</double>
				<double>0.699999988079071</double>
			</ArrayOfDouble>
		</Object>
		<Object refID="8" type="System.Collections.Generic.List`1[[System.Double, mscorlib, Version=4.0.0.0, Culture=neutral, PublicKeyToken=b77a5c561934e089]]">
			<ArrayOfDouble xmlns:xsd="http://www.w3.org/2001/XMLSchema" xmlns:xsi="http://www.w3.org/2001/XMLSchema-instance">
				<double>0</double>
				<double>10</double>
			</ArrayOfDouble>
		</Object>
		<Object refID="9" type="System.Collections.Generic.List`1[[System.Double, mscorlib, Version=4.0.0.0, Culture=neutral, PublicKeyToken=b77a5c561934e089]]">
			<ArrayOfDouble xmlns:xsd="http://www.w3.org/2001/XMLSchema" xmlns:xsi="http://www.w3.org/2001/XMLSchema-instance">
				<double>0.699999988079071</double>
			</ArrayOfDouble>
		</Object>
		<Object refID="10" type="System.Collections.Generic.List`1[[System.Double, mscorlib, Version=4.0.0.0, Culture=neutral, PublicKeyToken=b77a5c561934e089]]">
			<ArrayOfDouble xmlns:xsd="http://www.w3.org/2001/XMLSchema" xmlns:xsi="http://www.w3.org/2001/XMLSchema-instance">
				<double>0</double>
				<double>0</double>
			</ArrayOfDouble>
		</Object>
		<Object refID="11" type="System.Collections.Generic.List`1[[System.Double, mscorlib, Version=4.0.0.0, Culture=neutral, PublicKeyToken=b77a5c561934e089]]">
			<ArrayOfDouble xmlns:xsd="http://www.w3.org/2001/XMLSchema" xmlns:xsi="http://www.w3.org/2001/XMLSchema-instance">
				<double>0</double>
				<double>0</double>
			</ArrayOfDouble>
		</Object>
		<Object refID="12" type="System.Collections.Generic.List`1[[System.Double, mscorlib, Version=4.0.0.0, Culture=neutral, PublicKeyToken=b77a5c561934e089]]">
			<ArrayOfDouble xmlns:xsd="http://www.w3.org/2001/XMLSchema" xmlns:xsi="http://www.w3.org/2001/XMLSchema-instance">
				<double>0</double>
				<double>1</double>
			</ArrayOfDouble>
		</Object>
		<Object refID="13" type="System.Collections.Generic.List`1[[System.Double, mscorlib, Version=4.0.0.0, Culture=neutral, PublicKeyToken=b77a5c561934e089]]">
			<ArrayOfDouble xmlns:xsd="http://www.w3.org/2001/XMLSchema" xmlns:xsi="http://www.w3.org/2001/XMLSchema-instance">
				<double>0.550000011920929</double>
			</ArrayOfDouble>
		</Object>
		<Object refID="14" type="System.Collections.Generic.List`1[[System.Double, mscorlib, Version=4.0.0.0, Culture=neutral, PublicKeyToken=b77a5c561934e089]]">
			<ArrayOfDouble xmlns:xsd="http://www.w3.org/2001/XMLSchema" xmlns:xsi="http://www.w3.org/2001/XMLSchema-instance">
				<double>0</double>
				<double>2</double>
			</ArrayOfDouble>
		</Object>
		<Object refID="15" type="System.Collections.Generic.List`1[[System.Double, mscorlib, Version=4.0.0.0, Culture=neutral, PublicKeyToken=b77a5c561934e089]]">
			<ArrayOfDouble xmlns:xsd="http://www.w3.org/2001/XMLSchema" xmlns:xsi="http://www.w3.org/2001/XMLSchema-instance">
				<double>0.85000002384185791</double>
			</ArrayOfDouble>
		</Object>
		<Object refID="16" type="System.Collections.Generic.List`1[[System.Double, mscorlib, Version=4.0.0.0, Culture=neutral, PublicKeyToken=b77a5c561934e089]]">
			<ArrayOfDouble xmlns:xsd="http://www.w3.org/2001/XMLSchema" xmlns:xsi="http://www.w3.org/2001/XMLSchema-instance">
				<double>0</double>
				<double>3</double>
			</ArrayOfDouble>
		</Object>
		<Object refID="17" type="System.Collections.Generic.List`1[[System.Double, mscorlib, Version=4.0.0.0, Culture=neutral, PublicKeyToken=b77a5c561934e089]]">
			<ArrayOfDouble xmlns:xsd="http://www.w3.org/2001/XMLSchema" xmlns:xsi="http://www.w3.org/2001/XMLSchema-instance">
				<double>0.93000000715255737</double>
			</ArrayOfDouble>
		</Object>
		<Object refID="18" type="System.Collections.Generic.List`1[[System.String, mscorlib, Version=4.0.0.0, Culture=neutral, PublicKeyToken=b77a5c561934e089]]">
			<ArrayOfString xmlns:xsd="http://www.w3.org/2001/XMLSchema" xmlns:xsi="http://www.w3.org/2001/XMLSchema-instance">
				<string />
				<string>Gravel</string>
				<string>Soil</string>
				<string>WaterShallow</string>
			</ArrayOfString>
		</Object>
		<Object refID="19" type="System.Collections.Generic.List`1[[System.Double, mscorlib, Version=4.0.0.0, Culture=neutral, PublicKeyToken=b77a5c561934e089]]">
			<ArrayOfDouble xmlns:xsd="http://www.w3.org/2001/XMLSchema" xmlns:xsi="http://www.w3.org/2001/XMLSchema-instance">
				<double>1</double>
				<double>2</double>
				<double>3</double>
			</ArrayOfDouble>
		</Object>
	</Objects>
</NodeCanvas>