<?xml version="1.0" encoding="utf-8" ?>
<HistoryAutoRecorderGroupDefs>

  <HistoryAutoRecorderGroupDef>
    <defName>Food</defName>
    <label>Food</label>
    <graphLabelY>Amount</graphLabelY>
    <historyAutoRecorderDefs>
      <li>MealsTotal</li>
      <li>RawFoodTotal</li>
      <li>PlantFoodTotal</li>
  	</historyAutoRecorderDefs>
  </HistoryAutoRecorderGroupDef>

  <HistoryAutoRecorderGroupDef>
    <defName>Power</defName>
    <label>Power</label>
    <graphLabelY>W/Wd</graphLabelY>
    <historyAutoRecorderDefs>
      <li>StoredPower</li>
      <li>PowerGenerated</li>
      <li>PowerConsumed</li>
    </historyAutoRecorderDefs>
  </HistoryAutoRecorderGroupDef>
    
</HistoryAutoRecorderGroupDefs>