<?xml version="1.0" encoding="utf-8" ?>
<LanguageData>

  <AnimalChat.label>charla animal</AnimalChat.label>
  <AnimalChat.logRulesInitiator.rulesStrings>
    <li>r_logentry(p=5)->[INITIATOR_nameDef] [tamed] [RECIPIENT_nameDef].</li>
    <li>r_logentry->[INITIATOR_nameDef] sentado cerca de [RECIPIENT_nameDef] y hablando a [INITIATOR_objective] de sí mismo sobre [TalkTopicAny].</li>
    <li>r_logentry->[INITIATOR_nameDef] aproximado a [RECIPIENT_nameDef] mientras susurra a [INITIATOR_objective] de sí mismo sobre [TalkTopicAny].</li>
    <li>r_logentry->[INITIATOR_nameDef] se mantuvo cerca de [RECIPIENT_nameDef] mientras hablas a [INITIATOR_objective] de sí mismo sobre [TalkTopicAny].</li>
    <li>tamed->hace ruidos tranquilizadores hacia</li>
    <li>tamed->ofreció gestos lentos y amigables a</li>
    <li>tamed->hizo ruidos silenciosos a</li>
    <li>tamed->hizo ruidos de chasqueo felices an</li>
    <li>tamed->gesticuló suavemente y se acercó</li>
    <li>tamed->se acercó lentamente</li>
    <li>tamed->tocó suavemente</li>
    <li>tamed->calmado y animado</li>
    <li>tamed->respiración emparejada a</li>
    <li>tamed->tomó una postura baja mientras se acercaba</li>
    <li>tamed->no mostró miedo o enojo</li>
    <li>tamed->fingió falta de atención hacia</li>
    <li>tamed->tarareaba suavemente una canción en</li>
    <li>tamed->cantó una vieja canción de cuna en</li>
    <li>tamed->tocado suavemente con firmeza</li>
    <li>tamed->mostró una actitud relajada hacia</li>
    <li>tamed->se sentó pacientemente cerca</li>
    <li>tamed->susurró una historia sobre [TalkTopicAny] a</li>
  </AnimalChat.logRulesInitiator.rulesStrings>

  <TameAttempt.label>intento de domesticar</TameAttempt.label>
  <TameAttempt.logRulesInitiator.rulesStrings>
    <li>r_logentry->[INITIATOR_nameDef] intentó domesticar a [RECIPIENT_nameDef].</li>
    <li>r_logentry->[INITIATOR_nameDef] intento tener a [RECIPIENT_nameDef] bajo control.</li>
    <li>r_logentry->[INITIATOR_nameDef] intentó poner collarín a [RECIPIENT_nameDef].</li>
    <li>r_logentry->[INITIATOR_nameDef] exigió la obediencia de [RECIPIENT_nameDef].</li>
    <li>r_logentry->[INITIATOR_nameDef] llamó [RECIPIENT_nameDef] venir a [INITIATOR_objective].</li>
    <li>r_logentry->[INITIATOR_nameDef] trató de hacer que [RECIPIENT_nameDef] se sentase.</li>
    <li>r_logentry->[INITIATOR_nameDef] agarró a [RECIPIENT_nameDef] bruscamente y ladró la orden.</li>
    <li>r_logentry->[INITIATOR_nameDef] intentó sostener a [RECIPIENT_nameDef] y mantenerlo inmovil.</li>
    <li>r_logentry->[INITIATOR_nameDef] gritó una oden a [RECIPIENT_nameDef].</li>
    <li>r_logentry->[INITIATOR_nameDef] abofeteó a [RECIPIENT_nameDef] en una muestra de dominio.</li>
    <li>r_logentry->[INITIATOR_nameDef] orientó a [RECIPIENT_nameDef] de vuelta a la comunidad.</li>
    <li>r_logentry->[INITIATOR_nameDef] llamó a [RECIPIENT_nameDef] para volver a la comunidad.</li>
    <li>r_logentry->[INITIATOR_nameDef] tocó una parte vulnerable del cuerpo de [RECIPIENT_nameDef], exigiendo obediencia.</li>
    <li>r_logentry->[INITIATOR_nameDef] señaló al suelo, exigiendo que [RECIPIENT_nameDef] acudiera.</li>
    <li>r_logentry->[INITIATOR_nameDef] dió a [RECIPIENT_nameDef] su primera orden.</li>
  </TameAttempt.logRulesInitiator.rulesStrings>

  <TrainAttempt.label>intento de adiestra</TrainAttempt.label>
  <TrainAttempt.logRulesInitiator.rulesStrings>
    <li>r_logentry->[INITIATOR_nameDef] [trained] [RECIPIENT_nameDef].</li>
    <li>trained(p=2)->[tried] para adiestrar</li>
    <li>trained->[tried] para mostrar un nuevo truco a</li>
    <li>trained->[tried] para disciplinar</li>
    <li>trained->[tried] para instruir</li>
    <li>trained->[tried] para fomentar una nueva habilidad a</li>
    <li>trained->demostró una habilidad para</li>
    <li>trained->fomentó una nueva respuesta de</li>
    <li>tried->tried</li>
    <li>tried->attempted</li>
  </TrainAttempt.logRulesInitiator.rulesStrings>

  <Nuzzle.label>acariciar con hocico</Nuzzle.label>
  <Nuzzle.logRulesInitiator.rulesStrings>
    <li>r_logentry(p=2)->[INITIATOR_nameDef] [nuzzleadverb] [nuzzled] [RECIPIENT_nameDef].</li>
    <li>r_logentry->[INITIATOR_nameDef] [nuzzleadverb] frotado [INITIATOR_possessive] nariz contra [RECIPIENT_nameDef] de [rubbedpart].</li>
    <li>nuzzled(p=2)->acariciado con hocico</li>
    <li>nuzzled->acurrucado a</li>
    <li>nuzzleadverb(p=4)-></li>
    <li>nuzzleadverb->suavemente</li>
    <li>nuzzleadverb->alentador</li>
    <li>nuzzleadverb->felizmente</li>
    <li>nuzzleadverb->suavemente</li>
    <li>nuzzleadverb->de manera colaborativa</li>
    <li>nuzzleadverb->ligeramente</li>
    <li>nuzzleadverb->calurosamente</li>
    <li>nuzzleadverb->lastimeramente</li>
    <li>nuzzleadverb->cariñosamente</li>
    <li>nuzzleadverb->afectuosamente </li>
    <li>rubbedpart->pierna</li>
    <li>rubbedpart->rodilla</li>
    <li>rubbedpart->pie</li>
    <li>rubbedpart->codo</li>
    <li>rubbedpart->cadera</li>
    <li>rubbedpart->hombro</li>
    <li>rubbedpart->mano</li>
    <li>rubbedpart->cara</li>
    <li>rubbedpart->brazo</li>
  </Nuzzle.logRulesInitiator.rulesStrings>


</LanguageData>