<?xml version="1.0" encoding="utf-8" ?>
<LanguageData>
<SoilTilled.label>Возделанная земля</SoilTilled.label>
<SoilTilled.description>Пропашка почвы. Делай посадки культур правильно!

Скорость: 62%
Объём работ: 47
Привлекательность: 1
</SoilTilled.description>

<ClutterWoodTileA.label>деревянные панели</ClutterWoodTileA.label>
<ClutterWoodTileA.description>Чудо современной науки - деревянные панели из дерева.


Скорость: 130%
Объём работ: 14
Привлекательность: 3
</ClutterWoodTileA.description>

<WoodPlankFloor2.label>Паркет тип 2</WoodPlankFloor2.label>
<WoodPlankFloor2.description>Деревянный паркет. Теплый, уютный.


Скорость: 130%
Объём работ: 14
Привлекательность: 3</WoodPlankFloor2.description>

<WoodPlankFloor3.label>Паркет тип 3</WoodPlankFloor3.label>
<WoodPlankFloor3.description>Отшлифованные деревянные планки. Красиво и уютно.


Скорость: 130%
Объём работ: 14
Привлекательность: 3</WoodPlankFloor3.description>

<WoodPlankFloor4.label>Паркет тип 4</WoodPlankFloor4.label>
<WoodPlankFloor4.description>Деревянный паркет. Теплый, уютный.


Скорость: 130%
Объём работ: 14
Привлекательность: 3</WoodPlankFloor4.description>

<WoodPlankFloor5.label>Паркет тип 5</WoodPlankFloor5.label>
<WoodPlankFloor5.description>Деревянный паркет. Теплый, уютный.


Скорость: 130%
Объём работ: 14
Привлекательность: 3</WoodPlankFloor5.description>

<WoodPlankFloor6.label>Паркет тип 6</WoodPlankFloor6.label>
<WoodPlankFloor6.description>Деревянный паркет. Теплый, уютный.


Скорость: 130%
Объём работ: 14
Привлекательность: 3</WoodPlankFloor6.description>

<CeramicTile.label>Керам. покрытие</CeramicTile.label>
<CeramicTile.description>Утилитарная белая керамическая плитка. Неприглядный внешний вид. Высокая скорость передвижения.


Скорость: 130%
Объём работ: 20
Привлекательность: 3
</CeramicTile.description>

<DarkConcrete.label>Тёмный бетон</DarkConcrete.label>
<DarkConcrete.description>Быстросохнущий бетон. Неприглядный внешний вид. Высокая скорость передвижения. Вы должны сперва вырыть яму чтобы залить бетон.


Скорость: 100%
Объём работ: 20
Привлекательность: 2
</DarkConcrete.description>

<MetalTile2.label>Чёрное металл. покрытие</MetalTile2.label>
<MetalTile2.description>Металлическое покрытие для истинных злодеев. Мухахаха


Скорость: 130%
Объём работ: 14
Привлекательность: 3
</MetalTile2.description>

<MetalTile3.label>Тёмное металл. покрытие</MetalTile3.label>
<MetalTile3.description>Металлическое покрытие для истинных злодеев.


Скорость: 130%
Объём работ: 14
Привлекательность: 3
</MetalTile3.description>

<MetalTile4.label>Белое металл. покрытие</MetalTile4.label>
<MetalTile4.description>Почуствуй себя в звездолете!


Скорость: 130%
Объём работ: 14
Привлекательность: 3
</MetalTile4.description>

<CarpetBeige.label>Бежевый ковёр</CarpetBeige.label>
<CarpetBeige.description>Потрясающий бежевый ковёр, мягкий и успокаивающий.


Скорость: 118%
Объём работ: 25
Привлекательность: 4
</CarpetBeige.description>

<CarpetOrange.label>Оранжевый ковёр</CarpetOrange.label>
<CarpetOrange.description>Мягкий ковёр с ярким оттенком календулы.


Скорость: 118%
Объём работ: 25
Привлекательность: 4
</CarpetOrange.description>

<CarpetYellow.label>Желтый ковёр</CarpetYellow.label>
<CarpetYellow.description>Летний ковёр цвета Солнца. Того самого...


Скорость: 118%
Объём работ: 25
Привлекательность: 4
</CarpetYellow.description>

<CarpetTurquoise.label>Бирюзовый ковёр</CarpetTurquoise.label>
<CarpetTurquoise.description>Успокаивающий сине-зеленый ковёр.


Скорость: 118%
Объём работ: 25
Привлекательность: 4
</CarpetTurquoise.description>

<CarpetPurple.label>Фиолетовый ковёр</CarpetPurple.label>
<CarpetPurple.description>ковёр в величественном фиолетовом оттенке.


Скорость: 118%
Объём работ: 25
Привлекательность: 4
</CarpetPurple.description>

<CarpetWhite.label>Белый ковёр</CarpetWhite.label>
<CarpetWhite.description>Мягкий белый ковёр, выглядящий свежо и чисто.


Скорость: 118%
Объём работ: 25
Привлекательность: 4
</CarpetWhite.description>

<CarpetBlack.label>Чёрный ковёр</CarpetBlack.label>
<CarpetBlack.description>Плюшевый ковёр тёмного властелина.


Скорость: 118%
Объём работ: 25
Привлекательность: 4
</CarpetBlack.description>

<CheckCarpetRed.label>Клетчатый красный ковёр</CheckCarpetRed.label>
<CheckCarpetRed.description>Клетчатый ковёр цвета розы.


Скорость: 118%
Объём работ: 25
Привлекательность: 4
</CheckCarpetRed.description>

<CheckCarpetOrange.label>Клетчатый оранжевый ковёр</CheckCarpetOrange.label>
<CheckCarpetOrange.description>Клетчатый ковёр цвета календулы.


Скорость: 118%
Объём работ: 25
Привлекательность: 4
</CheckCarpetOrange.description>

<CheckCarpetYellow.label>Клетчатый жёлтый ковёр</CheckCarpetYellow.label>
<CheckCarpetYellow.description>Клетчатый ковёр цвета Солнца. Того самого...


Скорость: 118%
Объём работ: 25
Привлекательность: 4
</CheckCarpetYellow.description>

<CheckCarpetTurquoise.label>Клетчатый бирюзовый ковёр</CheckCarpetTurquoise.label>
<CheckCarpetTurquoise.description>Клетчатый ковёр цвета бирюзы.


Скорость: 118%
Объём работ: 25
Привлекательность: 4
</CheckCarpetTurquoise.description>

<CheckCarpetPurple.label>Клетчатый фиолетовый ковёр</CheckCarpetPurple.label>
<CheckCarpetPurple.description>Клетчатый ковёр притягательного фиолетового оттенка.


Скорость: 118%
Объём работ: 25
Привлекательность: 4
</CheckCarpetPurple.description>

<CheckCarpetWhite.label>Клетчатый белый ковёр</CheckCarpetWhite.label>
<CheckCarpetWhite.description>Красота неописуемая, но как отмывать?


Скорость: 118%
Объём работ: 25
Привлекательность: 4
</CheckCarpetWhite.description>

<CheckCarpetBlack.label>Клетчатый чёрный ковёр</CheckCarpetBlack.label>
<CheckCarpetBlack.description>Мрачно, стильно и готично. Идеальный вариант для гостиной темного властелина


Скорость: 118%
Объём работ: 25
Привлекательность: 4
</CheckCarpetBlack.description>

<CheckCarpetBlue.label>Клетчатый синий ковёр</CheckCarpetBlue.label>
<CheckCarpetBlue.description>У вас такое ощущение, что вас сейчас укачает.


Скорость: 118%
Объём работ: 25
Привлекательность: 4
</CheckCarpetBlue.description>

<CheckCarpetGreen.label>Клетчатый зеленый ковёр</CheckCarpetGreen.label>
<CheckCarpetGreen.description>Веселенький ковёр цвета лужайки.


Скорость: 118%
Объём работ: 25
Привлекательность: 4
</CheckCarpetGreen.description>

<GoldSolid.label>Пол из золота</GoldSolid.label>
<GoldSolid.description>Ну вы и богач.


Скорость: 130%
Объём работ: 30
Привлекательность: 10
</GoldSolid.description>

<RoughSandstoneFloor.label>Пол из грубого песчаника</RoughSandstoneFloor.label>
<RoughSandstoneFloor.description>Песчаник, выщербленный под воздействием стихий.


Скорость: 108%
Объём работ: 14
Привлекательность: -1
</RoughSandstoneFloor.description>

<RoughGraniteFloor.label>Пол из грубого гранита</RoughGraniteFloor.label>
<RoughGraniteFloor.description>Гранит, выщербленный под воздействием стихий.


Скорость: 108%
Объём работ: 14
Привлекательность: -1
</RoughGraniteFloor.description>

<RoughLimestoneFloor.label>Пол из грубого известняка</RoughLimestoneFloor.label>
<RoughLimestoneFloor.description>Известняк, выщербленный под воздействием стихий.


Скорость: 108%
Объём работ: 14
Привлекательность: -1
</RoughLimestoneFloor.description>

<RoughSlateFloor.label>Пол из грубого сланца</RoughSlateFloor.label>
<RoughSlateFloor.description>Сланец, выщербленный под воздействием стихий.


Скорость: 108%
Объём работ: 14
Привлекательность: -1
</RoughSlateFloor.description>

<RoughMarbleFloor.label>Пол из грубого мрамора</RoughMarbleFloor.label>
<RoughMarbleFloor.description>Мрамор, выщербленный под воздействием стихий.


Скорость: 108%
Объём работ: 14
Привлекательность: -1
</RoughMarbleFloor.description>

<FloorStoneSlabsSandstone.label>Аккуратные плиты из песчаника</FloorStoneSlabsSandstone.label>
<FloorStoneSlabsSandstone.description>Каменный пол из аккуратных квадратных плит песчаника.

Скорость: 118%
Объём работ: 19
Привлекательность: 3
</FloorStoneSlabsSandstone.description>

<FloorStoneSlabsGranite.label>Аккуратные плиты из гранита</FloorStoneSlabsGranite.label>
<FloorStoneSlabsGranite.description>Каменный пол из аккуратных квадратных плит гранита.

Скорость: 118%
Объём работ: 19
Привлекательность: 3
</FloorStoneSlabsGranite.description>

<FloorStoneSlabsLimestone.label>Аккуратные плиты из известянка</FloorStoneSlabsLimestone.label>
<FloorStoneSlabsLimestone.description>Каменный пол из аккуратных квадратных плит известняка.

Скорость: 118%
Объём работ: 19
Привлекательность: 3
</FloorStoneSlabsLimestone.description>

<FloorStoneSlabsSlate.label>Аккуратные плиты из сланца</FloorStoneSlabsSlate.label>
<FloorStoneSlabsSlate.description>Каменный пол из аккуратных квадратных плит сланца.

Скорость: 118%
Объём работ: 19
Привлекательность: 3
</FloorStoneSlabsSlate.description>

<FloorStoneSlabsMarble.label>Аккуратные плиты из мрамора</FloorStoneSlabsMarble.label>
<FloorStoneSlabsMarble.description>Каменный пол из аккуратных квадратных плит мрамора.

Скорость: 118%
Объём работ: 19
Привлекательность: 3
</FloorStoneSlabsMarble.description>

<FloorStoneHexSandstone.label>6-угольные плиты из песчаника</FloorStoneHexSandstone.label>
<FloorStoneHexSandstone.description>Каменный пол из аккуратных шестиугольных плит песчаника.

Скорость: 118%
Объём работ: 19
Привлекательность: 3
</FloorStoneHexSandstone.description>

<FloorStoneHexGranite.label>6-угольные плиты из гранита</FloorStoneHexGranite.label>
<FloorStoneHexGranite.description>Каменный пол из аккуратных шестиугольных плит гранита.

Скорость: 118%
Объём работ: 19
Привлекательность: 3
</FloorStoneHexGranite.description>

<FloorStoneHexLimestone.label>6-угольные плиты из известняка</FloorStoneHexLimestone.label>
<FloorStoneHexLimestone.description>Каменный пол из аккуратных шестиугольных плит известняка.

Скорость: 118%
Объём работ: 19
Привлекательность: 3
</FloorStoneHexLimestone.description>

<FloorStoneHexSlate.label>6-угольные плиты из сланца</FloorStoneHexSlate.label>
<FloorStoneHexSlate.description>Каменный пол из аккуратных шестиугольных плит сланца.

Скорость: 118%
Объём работ: 19
Привлекательность: 3</FloorStoneHexSlate.description>

<FloorStoneHexMarble.label>6-угольные плиты из мрамора</FloorStoneHexMarble.label>
<FloorStoneHexMarble.description>Каменный пол из аккуратных шестиугольных плит мрамора.

Скорость: 118%
Объём работ: 19
Привлекательность: 3</FloorStoneHexMarble.description>

<FloorStoneMosaicSandstone.label>Мозаика из песчаника</FloorStoneMosaicSandstone.label>
<FloorStoneMosaicSandstone.description>Каменный пол из аккуратной мозаики из песчаника.

Скорость: 118%
Объём работ: 19
Привлекательность: 3
</FloorStoneMosaicSandstone.description>

<FloorStoneMosaicGranite.label>Мозаика из гранита</FloorStoneMosaicGranite.label>
<FloorStoneMosaicGranite.description>Каменный пол из аккуратной гранитной мозаики.

Скорость: 118%
Объём работ: 19
Привлекательность: 3
</FloorStoneMosaicGranite.description>

<FloorStoneMosaicLimestone.label>Мозаика из известняка</FloorStoneMosaicLimestone.label>
<FloorStoneMosaicLimestone.description>Каменный пол из аккуратной известняковой мозаики.

Скорость: 118%
Объём работ: 19
Привлекательность: 3
</FloorStoneMosaicLimestone.description>

<FloorStoneMosaicSlate.label>Мозаика из сланца</FloorStoneMosaicSlate.label>
<FloorStoneMosaicSlate.description>Каменный пол из аккуратной мозаики из сланца.

Скорость: 118%
Объём работ: 19
Привлекательность: 3
</FloorStoneMosaicSlate.description>

<FloorStoneMosaicMarble.label>Мозаика из мрамора</FloorStoneMosaicMarble.label>
<FloorStoneMosaicMarble.description>Каменный пол из аккуратной мраморной мозаики.

Скорость: 118%
Объём работ: 19
Привлекательность: 3
</FloorStoneMosaicMarble.description>

<FloorStoneRoughSandstone.label>Грубые блоки песчаника</FloorStoneRoughSandstone.label>
<FloorStoneRoughSandstone.description>Каменный пол из грубых блоков песчаника.

Скорость: 118%
Объём работ: 19
Привлекательность: 3
</FloorStoneRoughSandstone.description>

<FloorStoneRoughGranite.label>Грубые блоки гранита</FloorStoneRoughGranite.label>
<FloorStoneRoughGranite.description>Каменный пол из грубых блоков гранита.

Скорость: 118%
Объём работ: 19
Привлекательность: 3
</FloorStoneRoughGranite.description>

<FloorStoneRoughLimestone.label>Грубые блоки известняка</FloorStoneRoughLimestone.label>
<FloorStoneRoughLimestone.description>Каменный пол из грубых блоков известняка.

Скорость: 118%
Объём работ: 19
Привлекательность: 3
</FloorStoneRoughLimestone.description>

<FloorStoneRoughSlate.label>Грубые блоки сланца</FloorStoneRoughSlate.label>
<FloorStoneRoughSlate.description>Каменный пол из грубых блоков сланца.

Скорость: 118%
Объём работ: 19
Привлекательность: 3
</FloorStoneRoughSlate.description>

<FloorStoneRoughMarble.label>Грубые блоки мрамора</FloorStoneRoughMarble.label>
<FloorStoneRoughMarble.description>Каменный пол из грубых блоков мрамора.

Скорость: 118%
Объём работ: 19
Привлекательность: 3
</FloorStoneRoughMarble.description>


<FloorStoneRandomSandstone.label>случайное мощение (песчаник)</FloorStoneRandomSandstone.label>
<FloorStoneRandomSandstone.description>Каменный пол из прямоугольных и квадратных блоков песчаника, расположенных случайным образом.

Скорость: 118%
Объём работ: 19
Привлекательность: 3
</FloorStoneRandomSandstone.description>

<FloorStoneRandomGranite.label>случайное мощение (гранит)</FloorStoneRandomGranite.label>
<FloorStoneRandomGranite.description>Каменный пол из прямоугольных и квадратных блоков гранита, расположенных случайным образом.

Скорость: 118%
Объём работ: 19
Привлекательность: 3 
</FloorStoneRandomGranite.description>

<FloorStoneRandomLimestone.label>случайное мощение (известняк)</FloorStoneRandomLimestone.label>
<FloorStoneRandomLimestone.description>Каменный пол из прямоугольных и квадратных блоков известняка, расположенных случайным образом.

Скорость: 118%
Объём работ: 19
Привлекательность: 3 
</FloorStoneRandomLimestone.description>

<FloorStoneRandomSlate.label>случайное мощение (сланец)</FloorStoneRandomSlate.label>
<FloorStoneRandomSlate.description>Каменный пол из из прямоугольных и квадратных блоков сланца, расположенных случайным образом.

Скорость: 118%
Объём работ: 19
Привлекательность: 3 
</FloorStoneRandomSlate.description>

<FloorStoneRandomMarble.label>случайное мощение (мрамор)</FloorStoneRandomMarble.label>
<FloorStoneRandomMarble.description>Каменный пол из из прямоугольных и квадратных блоков мрамора, расположенных случайным образом.

Скорость: 118%
Объём работ: 19
Привлекательность: 3 
</FloorStoneRandomMarble.description>

</LanguageData>