<?xml version="1.0" encoding="utf-8"?>
<LanguageData>
	<HiveAttackTarget>Drafted pawns attack hives(in vanilla enadbled by default)</HiveAttackTarget>
	<DropOneWithControl>Hold Ctrl to drop one item from the pawn inventory instead of a stack</DropOneWithControl>
	<BetterHostileReadouts>Show names for hostile animals</BetterHostileReadouts>
	<SkillArrows>Show up/down skill indicators</SkillArrows>
	<ResearchingArrow>Show research in progress indicator</ResearchingArrow>

	<AT_AllowedAreaTip>Shift + click: mass restrict allowed area\nCtrl + click: manage areas</AT_AllowedAreaTip>
</LanguageData>