<?xml version="1.0" encoding="utf-8"?>
<Patch>

	<!-- ==================== QuadrupedAnimalWithPawsAndTail ==================== -->

	<!-- ========== Add groups entry if it doesn't exist already ========== -->

	<Operation Class="PatchOperationConditional">
		<xpath>Defs/BodyDef[defName="QuadrupedAnimalWithPawsAndTail"]/corePart/groups</xpath>
		<nomatch Class="PatchOperationAdd">
			<xpath>Defs/BodyDef[defName="QuadrupedAnimalWithPawsAndTail"]/corePart</xpath>
			<value>
				<groups />
			</value>
		</nomatch>
	</Operation>

	<Operation Class="PatchOperationConditional">
		<xpath>Defs/BodyDef[defName="QuadrupedAnimalWithPawsAndTail"]/corePart/groups</xpath>
		<nomatch Class="PatchOperationAdd">
			<xpath>Defs/BodyDef[defName="QuadrupedAnimalWithPawsAndTail"]/corePart</xpath>
			<value>
				<groups />
			</value>
		</nomatch>
	</Operation>

	<Operation Class="PatchOperationConditional">
		<xpath>Defs/BodyDef[defName="QuadrupedAnimalWithPawsAndTail"]/corePart/parts/li[def="Tail"]/groups</xpath>
		<nomatch Class="PatchOperationAdd">
			<xpath>Defs/BodyDef[defName="QuadrupedAnimalWithPawsAndTail"]/corePart/parts/li[def="Tail"]</xpath>
			<value>
				<groups />
			</value>
		</nomatch>
	</Operation>

	<Operation Class="PatchOperationConditional">
		<xpath>Defs/BodyDef[defName="QuadrupedAnimalWithPawsAndTail"]/corePart/parts/li[def="Neck"]/groups</xpath>
		<nomatch Class="PatchOperationAdd">
			<xpath>Defs/BodyDef[defName="QuadrupedAnimalWithPawsAndTail"]/corePart/parts/li[def="Neck"]</xpath>
			<value>
				<groups />
			</value>
		</nomatch>
	</Operation>


	<Operation Class="PatchOperationConditional">
		<xpath>Defs/BodyDef[defName="QuadrupedAnimalWithPawsAndTail"]/corePart/parts/li[def="Neck"]/groups</xpath>
		<nomatch Class="PatchOperationAdd">
			<xpath>Defs/BodyDef[defName="QuadrupedAnimalWithPawsAndTail"]/corePart/parts/li[def="Neck"]</xpath>
			<value>
				<groups />
			</value>
		</nomatch>
	</Operation>

	<Operation Class="PatchOperationConditional">
		<xpath>Defs/BodyDef[defName="QuadrupedAnimalWithPawsAndTail"]/corePart/parts/li[def="Neck"]/parts/li[def="Head"]/groups</xpath>
		<nomatch Class="PatchOperationAdd">
			<xpath>Defs/BodyDef[defName="QuadrupedAnimalWithPawsAndTail"]/corePart/parts/li[def="Neck"]/parts/li[def="Head"]</xpath>
			<value>
				<groups />
			</value>
		</nomatch>
	</Operation>

	<Operation Class="PatchOperationConditional">
		<xpath>Defs/BodyDef[defName="QuadrupedAnimalWithPawsAndTail"]/corePart/parts/li[def="Neck"]/parts/li[def="Head"]/parts/li[def="AnimalJaw"]/groups</xpath>
		<nomatch Class="PatchOperationAdd">
			<xpath>Defs/BodyDef[defName="QuadrupedAnimalWithPawsAndTail"]/corePart/parts/li[def="Neck"]/parts/li[def="Head"]/parts/li[def="AnimalJaw"]</xpath>
			<value>
				<groups />
			</value>
		</nomatch>
	</Operation>

	<Operation Class="PatchOperationConditional">
		<xpath>Defs/BodyDef[defName="QuadrupedAnimalWithPawsAndTail"]/corePart/parts/li[def="Leg"]/groups</xpath>
		<nomatch Class="PatchOperationAdd">
			<xpath>Defs/BodyDef[defName="QuadrupedAnimalWithPawsAndTail"]/corePart/parts/li[def="Leg"]</xpath>
			<value>
				<groups />
			</value>
		</nomatch>
	</Operation>

	<Operation Class="PatchOperationConditional">
		<xpath>Defs/BodyDef[defName="QuadrupedAnimalWithPawsAndTail"]/corePart/parts/li[def="Leg"]/parts/li[def="Paw"]/groups</xpath>
		<nomatch Class="PatchOperationAdd">
			<xpath>Defs/BodyDef[defName="QuadrupedAnimalWithPawsAndTail"]/corePart/parts/li[def="Leg"]/parts/li[def="Paw"]</xpath>
			<value>
				<groups />
			</value>
		</nomatch>
	</Operation>

	<Operation Class="PatchOperationConditional">
		<xpath>Defs/BodyDef[defName="QuadrupedAnimalWithPawsAndTail"]/corePart/parts/li[def="Leg"]/parts/li[customLabel="rear left paw"]/groups</xpath>
		<nomatch Class="PatchOperationAdd">
			<xpath>Defs/BodyDef[defName="QuadrupedAnimalWithPawsAndTail"]/corePart/parts/li[def="Leg"]/parts/li[customLabel="rear left paw"]</xpath>
			<value>
				<groups />
			</value>
		</nomatch>
	</Operation>

	<Operation Class="PatchOperationConditional">
		<xpath>Defs/BodyDef[defName="QuadrupedAnimalWithPawsAndTail"]/corePart/parts/li[def="Leg"]/parts/li[customLabel="rear right paw"]/groups</xpath>
		<nomatch Class="PatchOperationAdd">
			<xpath>Defs/BodyDef[defName="QuadrupedAnimalWithPawsAndTail"]/corePart/parts/li[def="Leg"]/parts/li[customLabel="rear right paw"]</xpath>
			<value>
				<groups />
			</value>
		</nomatch>
	</Operation>

	<!-- ========== Add armor coverage ========== -->

	<Operation Class="PatchOperationAdd">
		<xpath>Defs/BodyDef[defName="QuadrupedAnimalWithPawsAndTail"]/corePart/groups</xpath>
		<value>
			<li>CoveredByNaturalArmor</li>
		</value>
	</Operation>

	<Operation Class="PatchOperationAdd">
		<xpath>Defs/BodyDef[defName="QuadrupedAnimalWithPawsAndTail"]/corePart/parts/li[def="Tail"]/groups</xpath>
		<value>
			<li>CoveredByNaturalArmor</li>
		</value>
	</Operation>

	<Operation Class="PatchOperationAdd">
		<xpath>Defs/BodyDef[defName="QuadrupedAnimalWithPawsAndTail"]/corePart/parts/li[def="Neck"]/groups</xpath>
		<value>
			<li>CoveredByNaturalArmor</li>
		</value>
	</Operation>

	<Operation Class="PatchOperationAdd">
		<xpath>Defs/BodyDef[defName="QuadrupedAnimalWithPawsAndTail"]/corePart/parts/li[def="Neck"]/parts/li[def="Head"]/groups</xpath>
		<value>
			<li>CoveredByNaturalArmor</li>
		</value>
	</Operation>

	<Operation Class="PatchOperationAdd">
		<xpath>Defs/BodyDef[defName="QuadrupedAnimalWithPawsAndTail"]/corePart/parts/li[def="Neck"]/parts/li[def="Head"]/parts/li[def="AnimalJaw"]/groups</xpath>
		<value>
			<li>CoveredByNaturalArmor</li>
		</value>
	</Operation>

	<Operation Class="PatchOperationAdd">
		<xpath>Defs/BodyDef[defName="QuadrupedAnimalWithPawsAndTail"]/corePart/parts/li[def="Leg"]/groups</xpath>
		<value>
			<li>CoveredByNaturalArmor</li>
		</value>
	</Operation>

	<Operation Class="PatchOperationAdd">
		<xpath>Defs/BodyDef[defName="QuadrupedAnimalWithPawsAndTail"]/corePart/parts/li[def="Leg"]/parts/li[def="Paw"]/groups</xpath>
		<value>
			<li>CoveredByNaturalArmor</li>
		</value>
	</Operation>

</Patch>